[{"name":"Goku","Descritpion":"I am a super saying trying to become a super dev","RepoUrl":"goke-strive@github.com","LiveUrl":"goke-strive@github.com","ID":"3jef54sfkihkoqq8"},{"name":"Guest","Descritpion":"Trying to look how tech words look like","RepoUrl":"guest-strive@github.com","LiveUrl":"guest-strive@github.com","ID":"3jef54tdkihkrivg"},{"name":"Guest","Descritpion":"Trying to look how tech words look like","RepoUrl":"guest-strive@github.com","LiveUrl":"guest-strive@github.com","ID":"3jef555ckihmjxuj"},{"name":"Bla blat","Descritpion":"balsklasjlas","RepoUrl":"guesslndjnadjm","LiveUrl":"gueshdjhdjhdjhs","ID":"3jef55kukihmkfjc"},{"name":"Bla blat","Descritpion":"balsklasjlas","RepoUrl":"guesslndjnadjm","LiveUrl":"gueshdjhdjhdjhs","ID":"3jef55l0kihmkhoo"}]